searchnets/__about__.py
searchnets/__init__.py
searchnets/__main__.py
searchnets/assay.py
searchnets/data.py
searchnets/tensorboard.py
searchnets/test.py
searchnets/train.py
searchnets/analysis/__init__.py
searchnets/analysis/searchstims.py
searchnets/analysis/vsd.py
searchnets/config/__init__.py
searchnets/config/data.py
searchnets/config/parse.py
searchnets/config/test.py
searchnets/config/train.py
searchnets/datasets/__init__.py
searchnets/datasets/searchstims.py
searchnets/datasets/voc.py
searchnets/engine/__init__.py
searchnets/engine/abstract_trainer.py
searchnets/engine/tester.py
searchnets/engine/trainer.py
searchnets/engine/transfer_trainer.py
searchnets/engine/voc_assayer.py
searchnets/nets/__init__.py
searchnets/nets/alexnet.py
searchnets/nets/cornet.py
searchnets/nets/cornet_modules.py
searchnets/nets/cornet_rt.py
searchnets/nets/cornet_s.py
searchnets/nets/cornet_z.py
searchnets/nets/detectnet.py
searchnets/nets/layers.py
searchnets/nets/vgg16.py
searchnets/plot/__init__.py
searchnets/plot/heatmaps.py
searchnets/plot/setsize.py
searchnets/plot/trainhistory.py
searchnets/transforms/__init__.py
searchnets/transforms/functional.py
searchnets/transforms/transforms.py
searchnets/transforms/util.py
searchnets/utils/__init__.py
searchnets/utils/general.py
visual_search_nets-1.2.0.dist-info/LICENSE
visual_search_nets-1.2.0.dist-info/METADATA
visual_search_nets-1.2.0.dist-info/WHEEL
visual_search_nets-1.2.0.dist-info/entry_points.txt
visual_search_nets-1.2.0.dist-info/top_level.txt
visual_search_nets-1.2.0.dist-info/RECORD
