Metadata-Version: 2.1
Name: visual-search-nets
Version: 1.2.0
Summary: neural network models of visual search behavior
Home-page: https://github.com/NickleDave/visual-search-nets
Author: David Nicholson
Author-email: nicholdav@gmail.com
License: BSD
Platform: UNKNOWN
Classifier: License :: OSI Approved :: BSD License
Classifier: Programming Language :: Python
Classifier: Programming Language :: Python :: 3
Classifier: Programming Language :: Python :: 3.6
Classifier: Programming Language :: Python :: Implementation :: CPython
Requires-Python: >=3.6.0
Requires-Dist: attrs
Requires-Dist: imageio
Requires-Dist: joblib
Requires-Dist: numpy
Requires-Dist: matplotlib
Requires-Dist: pandas
Requires-Dist: pyprojroot
Requires-Dist: scikit-learn
Requires-Dist: scipy
Requires-Dist: searchstims (>=2.3.1)
Requires-Dist: seaborn
Requires-Dist: tensorboard
Requires-Dist: torch
Requires-Dist: torchvision
Requires-Dist: tqdm
